molbloom/__init__.py
molbloom/bloom.cpython-312-x86_64-linux-gnu.so
molbloom/common.py
molbloom/py.typed
molbloom/version.py
molbloom/data/zinc-instock-mini.bloom
molbloom-3.0.0.dist-info/METADATA
molbloom-3.0.0.dist-info/WHEEL
molbloom-3.0.0.dist-info/top_level.txt
molbloom-3.0.0.dist-info/RECORD
molbloom-3.0.0.dist-info/licenses/LICENSE
